{
  "meta": {
    "name": "eovie rsi/sma crossover",
    "author": "original author",
    "timeframe": "5m"
  },
  "indicators": [],
  "conditions": {
    "entry_long": [],
    "exit_long": [],
    "entry_short": [],
    "exit_short": []
  },
  "orders": [
    {
      "type": "market",
      "side": "long",
      "size": "pct:10",
      "reduce_only": false,
      "size_parsed": {
        "mode": "percent",
        "value": 10.0
      }
    }
  ],
  "position_sizing": {
    "mode": "percent",
    "value": 10.0
  },
  "timeframes": [
    "5m"
  ],
  "metadata": {
    "version": "0.1",
    "source": "python_parser"
  }
}